vplotter/__init__.py
vplotter/vplotter.py
vplotter/engines/__init__.py
vplotter/engines/bot_engine.py
vplotter/engines/gnuplot_engine.py
vplotter/engines/plotter_utils.py
vplotter/engines/veusz_engine.py
vplotter/tests/__init__.py
vplotter-1.3.4.dist-info/LICENSE.txt
vplotter-1.3.4.dist-info/METADATA
vplotter-1.3.4.dist-info/WHEEL
vplotter-1.3.4.dist-info/top_level.txt
vplotter-1.3.4.dist-info/RECORD
