Metadata-Version: 2.1
Name: vplotter
Version: 1.3.4
Summary: Plotter is a minimalistic handler to use plotting engines. See details for engine availability.
Home-page: https://github.com/AlexanderDKazakov/Plotter
Author: Alexander D. Kazakov, Varvara M. Prokacheva
Author-email: alexander.d.kazakov@gmail.com
License: MIT
Keywords: plot
Platform: UNKNOWN
Classifier: Development Status :: 4 - Beta
Classifier: Intended Audience :: Developers
Classifier: Topic :: Software Development :: Build Tools
Classifier: License :: OSI Approved :: MIT License
Classifier: Programming Language :: Python :: 3
Classifier: Programming Language :: Python :: 3.8
Classifier: Programming Language :: Python :: 3.9
Requires-Python: >=3.7
Requires-Dist: storer
Requires-Dist: numpy
Requires-Dist: pygnuplot
Requires-Dist: pandas
